./LICENSE
./PKG-INFO
./README.md
./__init__.py
./openapi.json
./pyproject.toml
./server.py
bach_tiktok_unauthorized_api_scraper_no_watermark_analytics_feed-1.0.0.dist-info/METADATA
bach_tiktok_unauthorized_api_scraper_no_watermark_analytics_feed-1.0.0.dist-info/WHEEL
bach_tiktok_unauthorized_api_scraper_no_watermark_analytics_feed-1.0.0.dist-info/entry_points.txt
bach_tiktok_unauthorized_api_scraper_no_watermark_analytics_feed-1.0.0.dist-info/licenses/LICENSE
bach_tiktok_unauthorized_api_scraper_no_watermark_analytics_feed-1.0.0.dist-info/RECORD
