Metadata-Version: 2.4
Name: bach-tiktok_unauthorized_api_scraper_no_watermark_analytics_feed
Version: 1.0.0
Summary: MCP server for accessing Tiktok Unauthorized Api Scraper No Watermark Analytics Feed API
Project-URL: Homepage, https://github.com/bachstudio/bach-tiktok_unauthorized_api_scraper_no_watermark_analytics_feed
Project-URL: Repository, https://github.com/bachstudio/bach-tiktok_unauthorized_api_scraper_no_watermark_analytics_feed
Project-URL: Documentation, https://github.com/bachstudio/bach-tiktok_unauthorized_api_scraper_no_watermark_analytics_feed#readme
Project-URL: Bug Tracker, https://github.com/bachstudio/bach-tiktok_unauthorized_api_scraper_no_watermark_analytics_feed/issues
Author: bachstudio
License: MIT License
License-File: LICENSE
Keywords: api,mcp,model-context-protocol,tiktok_unauthorized_api_scraper_no_watermark_analytics_feed
Classifier: Development Status :: 4 - Beta
Classifier: Intended Audience :: Developers
Classifier: License :: OSI Approved :: MIT License
Classifier: Programming Language :: Python :: 3
Classifier: Programming Language :: Python :: 3.10
Classifier: Programming Language :: Python :: 3.11
Classifier: Programming Language :: Python :: 3.12
Requires-Python: >=3.10
Requires-Dist: fastmcp>=2.0.0
Requires-Dist: httpx>=0.25.0
Provides-Extra: dev
Requires-Dist: black>=23.0.0; extra == 'dev'
Requires-Dist: pytest>=7.0.0; extra == 'dev'
